hpyhrtbase/__init__.py
hpyhrtbase/config.py
hpyhrtbase/hpyhrt_context.py
hpyhrtbase/init_app_base.py
hpyhrtbase/log.py
hpyhrtbase/py.typed
hpyhrtbase/model/__init__.py
hpyhrtbase/model/common_result.py
hpyhrtbase/model/error_info.py
hpyhrtbase/model/error_info_exception.py
hpyhrtbase/model/error_response.py
hpyhrtbase/model/errors.py
hpyhrtbase/utils/__init__.py
hpyhrtbase/utils/check_util.py
hpyhrtbase/utils/collection_util.py
hpyhrtbase/utils/config_util.py
hpyhrtbase/utils/debug_util.py
hpyhrtbase/utils/func_util.py
hpyhrtbase/utils/io_util.py
hpyhrtbase/utils/log_util.py
hpyhrtbase/utils/mail_util.py
hpyhrtbase/utils/object_util.py
hpyhrtbase/utils/random_util.py
hpyhrtbase/utils/str_util.py
hpyhrtbase/utils/throttle.py
hpyhrtbase/utils/time_util.py
hpyhrtbase-0.1.dist-info/METADATA
hpyhrtbase-0.1.dist-info/WHEEL
hpyhrtbase-0.1.dist-info/top_level.txt
hpyhrtbase-0.1.dist-info/RECORD
