Metadata-Version: 2.4
Name: hpyhrtbase
Version: 0.1
Summary: hpyhrt base
Keywords: hpyhrt
Classifier: Programming Language :: Python :: 3
Requires-Python: >=3.10
Requires-Dist: pydantic
Requires-Dist: pyhocon
Requires-Dist: requests
